rnbip_emulator/__init__.py
rnbip_emulator/__main__.py
rnbip_emulator/emulator_backend.py
rnbip_emulator/emulator_gui.py
rnbip_emulator/emulator_io.py
rnbip_emulator/machCode.bin
rnbip_emulator/rnbip_assembler.py
rnbip_emulator/rnbip_isa.py
rnbip_emulator/rnbip_mainwindow_ui.py
rnbip_emulator/asset/C_no.png
rnbip_emulator/asset/C_yes.png
rnbip_emulator/asset/Capture.PNG
rnbip_emulator/asset/Capture2.png
rnbip_emulator/asset/Capture3.png
rnbip_emulator/asset/Capture_IR.PNG
rnbip_emulator/asset/Capture_final.png
rnbip_emulator/asset/Capture_x.png
rnbip_emulator/asset/D_SP.png
rnbip_emulator/asset/Databus.png
rnbip_emulator/asset/E_FL.png
rnbip_emulator/asset/E_IP.png
rnbip_emulator/asset/E_OR.png
rnbip_emulator/asset/E_PC.png
rnbip_emulator/asset/E_R0.png
rnbip_emulator/asset/E_RN.png
rnbip_emulator/asset/E_SP.png
rnbip_emulator/asset/I_PC.png
rnbip_emulator/asset/I_SP.png
rnbip_emulator/asset/L_IR.png
rnbip_emulator/asset/L_OP.png
rnbip_emulator/asset/L_OR.png
rnbip_emulator/asset/L_PC.png
rnbip_emulator/asset/L_R0.png
rnbip_emulator/asset/L_RN.png
rnbip_emulator/asset/L_SP.png
rnbip_emulator/asset/OD_PC.png
rnbip_emulator/asset/OP_no.png
rnbip_emulator/asset/OP_yes.png
rnbip_emulator/asset/P_no.png
rnbip_emulator/asset/P_yes.png
rnbip_emulator/asset/R0_AS.png
rnbip_emulator/asset/RD.png
rnbip_emulator/asset/SAF_activated.png
rnbip_emulator/asset/S_AL.png
rnbip_emulator/asset/S_IF.png
rnbip_emulator/asset/S_PC.png
rnbip_emulator/asset/S_SP.png
rnbip_emulator/asset/WR.png
rnbip_emulator/asset/Z_no.png
rnbip_emulator/asset/Z_yes.png
rnbip_emulator/asset/back_final.png
rnbip_emulator/asset/killEOR.png
rnbip_emulator/asset/killEPC.png
rnbip_emulator/asset/killLPC.png
rnbip_emulator/asset/killLR0.png
rnbip_emulator/asset/killLRN2.png
rnbip_emulator/asset/specialPath.png
RNBIP2-1.6.2.dist-info/METADATA
RNBIP2-1.6.2.dist-info/WHEEL
RNBIP2-1.6.2.dist-info/entry_points.txt
RNBIP2-1.6.2.dist-info/top_level.txt
RNBIP2-1.6.2.dist-info/RECORD
