Metadata-Version: 2.1
Name: RNBIP2
Version: 1.6.2
Summary: RNBIP ISA Emulator
Home-page: https://github.com/digital-design-snu/RNBIP
Author: Paul George
Author-email: command.paul@gmail.com
Keywords: sample,setuptools,development
Classifier: Development Status :: 3 - Alpha
Classifier: Intended Audience :: Developers
Classifier: License :: OSI Approved :: MIT License
Classifier: Programming Language :: Python :: 3
Classifier: Programming Language :: Python :: 3.6
Classifier: Programming Language :: Python :: 3.7
Classifier: Programming Language :: Python :: 3.8
Classifier: Programming Language :: Python :: 3.9
Classifier: Programming Language :: Python :: 3 :: Only
Requires-Python: >=3.6, <4
Requires-Dist: PyQt5
